fm128_radar/__init__.py
fm128_radar/write_fm128_radar.py
fm128_radar-1.2.0.dist-info/METADATA
fm128_radar-1.2.0.dist-info/RECORD
fm128_radar-1.2.0.dist-info/WHEEL
fm128_radar-1.2.0.dist-info/top_level.txt
