Metadata-Version: 2.1
Name: fm128-radar
Version: 1.2.0
Summary: A python library to convert netCDF files to WRFDA supported fm128_radar ascii files
Home-page: https://github.com/ERA-URBAN/fm128_radar
Author: Ronald van Haren
Author-email: r.vanharen@esciencecenter.nl
License: Apache 2.0
Keywords: WRFDA netCDF WRF radar
Platform: UNKNOWN
Classifier: Development Status :: 5 - Production/Stable
Classifier: Topic :: Software Development :: Libraries :: Python Modules
Classifier: License :: OSI Approved :: Apache Software License
Requires-Dist: numpy
